<?xml version="1.0" encoding="UTF-8"?>
    <DTE xmlns="http://www.sii.cl/SiiDte" version="1.0">
    <Documento ID="F5337T33">
            <Encabezado>
                <IdDoc>
                    <TipoDTE>33</TipoDTE>
                    <Folio>5337</Folio>
                    <FchEmis>2019-02-21</FchEmis>
                    <FchVenc>2019-02-28</FchVenc>
                </IdDoc>
                <Emisor>
                    <RUTEmisor>76254347-8</RUTEmisor>
                    <RznSoc>HANWHA Q CELLS TIL TIL UNO SPA</RznSoc>
                    <GiroEmis>GENERACION EN OTRAS CENTRALES</GiroEmis>
                    <Acteco>741400</Acteco>
                    <DirOrigen>AVDA. APOQUINDO 3910, PISO 5</DirOrigen>
                    <CmnaOrigen>LAS CONDES </CmnaOrigen>
                    <CiudadOrigen>SANTIAGO</CiudadOrigen>
                    <CdgVendedor>No</CdgVendedor>
                </Emisor>
                <Receptor>
                    <RUTRecep>76489426-K</RUTRecep>
                    <RznSocRecep>AELA GENERACION SA</RznSocRecep>
                    <GiroRecep>DISTRIBUCION DE ENERGIA ELECTRICA</GiroRecep>
                    <Contacto>FELIPELATORRE@MAINSTREAMRPCOM</Contacto>
                    <DirRecep>AV. APOQUINDO 4800, TORRE 2, PISO 15, OFICINA 1501</DirRecep>
                    <CmnaRecep>LAS CONDES</CmnaRecep>
                    <CiudadRecep>SANTIAGO</CiudadRecep>
                </Receptor>
                <Totales>
                    <MntNeto>234701</MntNeto>
                    <MntExe>0</MntExe>
                    <TasaIVA>19</TasaIVA>
                    <IVA>44593</IVA>
                    <MntTotal>279294</MntTotal>
                </Totales>
            </Encabezado><Detalle>
        <NroLinDet>1</NroLinDet>
        <CdgItem>
            <TpoCodigo>INT</TpoCodigo>
            <VlrCodigo>1</VlrCodigo>
        </CdgItem>
        <NmbItem>ENERGIA
</NmbItem>
        <QtyItem>1</QtyItem>
        <UnmdItem>UN</UnmdItem>
        <PrcItem>234701</PrcItem>
        <MontoItem>234701</MontoItem>
    </Detalle>
    <Referencia>
        <NroLinRef>1</NroLinRef>
        <TpoDocRef>SEN</TpoDocRef>
        <FolioRef>DE00982A19C27S0340</FolioRef>
        <FchRef>2019-02-20</FchRef>
        <RazonRef>SEN_[TEE_][Ene19][L][V01]</RazonRef>
    </Referencia></Documento>
    </DTE>