<?xml version="1.0" encoding="UTF-8"?>
<SetDTE version="1.0">
  <EnvioDTE ID="76254347-8F285T61">
    <Caratula>
      <RutEmisor>76254347-8</RutEmisor>
      <NroDetalles>1</NroDetalles>
      <FechaHoraEnvio>2019-04-17T10:30:09</FechaHoraEnvio>
    </Caratula>
    <DocumentoDTE>
      <TipoDTE>61</TipoDTE>
      <Folio>285</Folio>
      <EstadoDTE>0</EstadoDTE>
      <GlosaEstadoDTE>DTE RECIBIDO OK</GlosaEstadoDTE>
      <PDF Url="https://sistema.webfactura.net/pdf/d19bc16ebb7ad45b6314881d617781d1" Timbre="https://sistema.webfactura.net/pdf/d19bc16ebb7ad45b6314881d617781d1/2"/>
    </DocumentoDTE>
  </EnvioDTE>
</SetDTE>
