<?xml version="1.0" encoding="UTF-8"?>
<SetDTE version="1.0">
  <EnvioDTE ID="76254347-8F3809T33">
    <Caratula>
      <RutEmisor>76254347-8</RutEmisor>
      <NroDetalles>1</NroDetalles>
      <FechaHoraEnvio>2018-12-13T23:52:05</FechaHoraEnvio>
    </Caratula>
    <DocumentoDTE>
      <TipoDTE>33</TipoDTE>
      <Folio>3809</Folio>
      <EstadoDTE>0</EstadoDTE>
      <GlosaEstadoDTE>DTE RECIBIDO OK</GlosaEstadoDTE>
      <PDF Url="https://sistema.webfactura.net/pdf/bd6c1c9fb4553f91d4128ce7ccd99d3b"
       Timbre="https://sistema.webfactura.net/pdf/bd6c1c9fb4553f91d4128ce7ccd99d3b/2"/>
    </DocumentoDTE>
  </EnvioDTE>
</SetDTE>
