<?xml version="1.0" encoding="UTF-8"?>
<SetDTE version="1.0">
  <EnvioDTE ID="76254347-8F5337T33">
    <Caratula>
      <RutEmisor>76254347-8</RutEmisor>
      <NroDetalles>1</NroDetalles>
      <FechaHoraEnvio>2019-02-21T11:44:45</FechaHoraEnvio>
    </Caratula>
    <DocumentoDTE>
      <TipoDTE>33</TipoDTE>
      <Folio>5337</Folio>
      <EstadoDTE>0</EstadoDTE>
      <GlosaEstadoDTE>DTE RECIBIDO OK</GlosaEstadoDTE>
      <PDF Url="https://sistema.webfactura.net/pdf/b91de6113684adb2cf9f382a7d0efb26" Timbre="https://sistema.webfactura.net/pdf/b91de6113684adb2cf9f382a7d0efb26/2"/>
    </DocumentoDTE>
  </EnvioDTE>
</SetDTE>
