<?xml version="1.0" encoding="UTF-8"?>
<SetDTE version="1.0">
  <EnvioDTE ID="76254347-8F5366T33">
    <Caratula>
      <RutEmisor>76254347-8</RutEmisor>
      <NroDetalles>1</NroDetalles>
      <FechaHoraEnvio>2019-02-21T12:22:52</FechaHoraEnvio>
    </Caratula>
    <DocumentoDTE>
      <TipoDTE>33</TipoDTE>
      <Folio>5366</Folio>
      <EstadoDTE>0</EstadoDTE>
      <GlosaEstadoDTE>DTE RECIBIDO OK</GlosaEstadoDTE>
      <PDF Url="https://sistema.webfactura.net/pdf/8c5787f1610f3155b3ebb86b7b7d142a" Timbre="https://sistema.webfactura.net/pdf/8c5787f1610f3155b3ebb86b7b7d142a/2"/>
    </DocumentoDTE>
  </EnvioDTE>
</SetDTE>
