<?xml version="1.0" encoding="UTF-8"?>
<SetDTE version="1.0">
  <EnvioDTE ID="76254347-8F5644T33">
    <Caratula>
      <RutEmisor>76254347-8</RutEmisor>
      <NroDetalles>1</NroDetalles>
      <FechaHoraEnvio>2019-04-12T19:56:27</FechaHoraEnvio>
    </Caratula>
    <DocumentoDTE>
      <TipoDTE>33</TipoDTE>
      <Folio>5644</Folio>
      <EstadoDTE>0</EstadoDTE>
      <GlosaEstadoDTE>DTE RECIBIDO OK</GlosaEstadoDTE>
      <PDF Url="https://sistema.webfactura.net/pdf/7b3bd12816daec94b3bb8e8aafab4b86" Timbre="https://sistema.webfactura.net/pdf/7b3bd12816daec94b3bb8e8aafab4b86/2"/>
    </DocumentoDTE>
  </EnvioDTE>
</SetDTE>
