<?xml version="1.0" encoding="UTF-8"?>
<SetDTE version="1.0">
  <EnvioDTE ID="76254347-8F5919T33">
    <Caratula>
      <RutEmisor>76254347-8</RutEmisor>
      <NroDetalles>1</NroDetalles>
      <FechaHoraEnvio>2019-05-22T9:12:41</FechaHoraEnvio>
    </Caratula>
    <DocumentoDTE>
      <TipoDTE>33</TipoDTE>
      <Folio>5919</Folio>
      <EstadoDTE>0</EstadoDTE>
      <GlosaEstadoDTE>DTE RECIBIDO OK</GlosaEstadoDTE>
      <PDF Url="https://sistema.webfactura.net/pdf/da0218d591665df345113ae23e10aeca" Timbre="https://sistema.webfactura.net/pdf/da0218d591665df345113ae23e10aeca/2"/>
    </DocumentoDTE>
  </EnvioDTE>
</SetDTE>
