<?xml version="1.0" encoding="UTF-8"?>
<SetDTE version="1.0">
  <EnvioDTE ID="76254347-8F5944T33">
    <Caratula>
      <RutEmisor>76254347-8</RutEmisor>
      <NroDetalles>1</NroDetalles>
      <FechaHoraEnvio>2019-05-22T9:17:07</FechaHoraEnvio>
    </Caratula>
    <DocumentoDTE>
      <TipoDTE>33</TipoDTE>
      <Folio>5944</Folio>
      <EstadoDTE>0</EstadoDTE>
      <GlosaEstadoDTE>DTE RECIBIDO OK</GlosaEstadoDTE>
      <PDF Url="https://sistema.webfactura.net/pdf/97ab6ea8193e6b578e548f4d7fce6592" Timbre="https://sistema.webfactura.net/pdf/97ab6ea8193e6b578e548f4d7fce6592/2"/>
    </DocumentoDTE>
  </EnvioDTE>
</SetDTE>
