<?xml version="1.0" encoding="UTF-8"?>
<SetDTE version="1.0">
  <EnvioDTE ID="76254347-8F6314T33">
    <Caratula>
      <RutEmisor>76254347-8</RutEmisor>
      <NroDetalles>1</NroDetalles>
      <FechaHoraEnvio>2019-08-22T11:10:38</FechaHoraEnvio>
    </Caratula>
    <DocumentoDTE>
      <TipoDTE>33</TipoDTE>
      <Folio>6314</Folio>
      <EstadoDTE>0</EstadoDTE>
      <GlosaEstadoDTE>DTE RECIBIDO OK</GlosaEstadoDTE>
      <PDF Url="https://sistema.webfactura.net/pdf/9d185f13b5ada2964cbb6d4b1e39ec2c" Timbre="https://sistema.webfactura.net/pdf/9d185f13b5ada2964cbb6d4b1e39ec2c/2"/>
    </DocumentoDTE>
  </EnvioDTE>
</SetDTE>
