<?xml version="1.0" encoding="UTF-8"?>
<SetDTE version="1.0">
  <EnvioDTE ID="76254347-8F6876T33">
    <Caratula>
      <RutEmisor>76254347-8</RutEmisor>
      <NroDetalles>1</NroDetalles>
      <FechaHoraEnvio>2020-01-22T18:56:42</FechaHoraEnvio>
    </Caratula>
    <DocumentoDTE>
      <TipoDTE>33</TipoDTE>
      <Folio>6876</Folio>
      <EstadoDTE>0</EstadoDTE>
      <GlosaEstadoDTE>DTE RECIBIDO OK</GlosaEstadoDTE>
      <PDF Url="https://sistema.webfactura.cl/pdf/0cc731028a92f1027c9f820fb030bb57" Timbre="https://sistema.webfactura.cl/pdf/0cc731028a92f1027c9f820fb030bb57/2"/>
    </DocumentoDTE>
  </EnvioDTE>
</SetDTE>
