<?xml version="1.0" encoding="UTF-8"?>
<SetDTE version="1.0">
  <EnvioDTE ID="76254347-8F7123T33">
    <Caratula>
      <RutEmisor>76254347-8</RutEmisor>
      <NroDetalles>1</NroDetalles>
      <FechaHoraEnvio>2020-04-21T20:43:32</FechaHoraEnvio>
    </Caratula>
    <DocumentoDTE>
      <TipoDTE>33</TipoDTE>
      <Folio>7123</Folio>
      <EstadoDTE>0</EstadoDTE>
      <GlosaEstadoDTE>DTE RECIBIDO OK</GlosaEstadoDTE>
      <PDF Url="https://sistema.webfactura.cl/pdf/6a019459c8437b0968de45550e657ce5" Timbre="https://sistema.webfactura.cl/pdf/6a019459c8437b0968de45550e657ce5/2"/>
    </DocumentoDTE>
  </EnvioDTE>
</SetDTE>
