<?xml version="1.0" encoding="UTF-8"?>
<SetDTE version="1.0">
  <EnvioDTE ID="76254347-8F7328T33">
    <Caratula>
      <RutEmisor>76254347-8</RutEmisor>
      <NroDetalles>1</NroDetalles>
      <FechaHoraEnvio>2020-06-20T15:14:55</FechaHoraEnvio>
    </Caratula>
    <DocumentoDTE>
      <TipoDTE>33</TipoDTE>
      <Folio>7328</Folio>
      <EstadoDTE>0</EstadoDTE>
      <GlosaEstadoDTE>DTE RECIBIDO OK</GlosaEstadoDTE>
      <PDF Url="https://sistema.webfactura.cl/pdf/16dcfe381d33f0ec59604e9328e5ff00" Timbre="https://sistema.webfactura.cl/pdf/16dcfe381d33f0ec59604e9328e5ff00/2"/>
    </DocumentoDTE>
  </EnvioDTE>
</SetDTE>
