<?xml version="1.0" encoding="UTF-8"?>
    <DTE xmlns="http://www.sii.cl/SiiDte" version="1.0">
    <Documento ID="F6966T33">
            <Encabezado>
                <IdDoc>
                    <TipoDTE>33</TipoDTE>
                    <Folio>6966</Folio>
                    <FchEmis>2020-02-20</FchEmis>
                    <FchVenc>2020-02-21</FchVenc>
                </IdDoc>
                <Emisor>
                    <RUTEmisor>76254347-8</RUTEmisor>
                    <RznSoc>HANWHA Q CELLS TIL TIL UNO SPA</RznSoc>
                    <GiroEmis>GENERACION ENER EN OTRAS CENTRALES N.C.P</GiroEmis>
                    <Acteco>351019</Acteco>
                    <DirOrigen>AV.APOQUINDO 5400 PISO 21 of 2101</DirOrigen>
                    <CmnaOrigen>LAS CONDES </CmnaOrigen>
                    <CiudadOrigen>SANTIAGO</CiudadOrigen>
                    <CdgVendedor>No</CdgVendedor>
                </Emisor>
                <Receptor>
                    <RUTRecep>76729711-4</RUTRecep>
                    <RznSocRecep>COMPANIA TRASMISORA LA CEBADA S.A.</RznSocRecep>
                    <GiroRecep>TRANSMISION DE ENERGIA ELECTRICA</GiroRecep>
                    <Contacto> MARIANGEL.RIVEROS@EPMCHILE.COM</Contacto>
                    <DirRecep>ROSARIO NORTE N 532 Piso 19</DirRecep>
                    <CmnaRecep>LAS CONDES</CmnaRecep>
                    <CiudadRecep>SANTIAGO</CiudadRecep>
                </Receptor>
                <Totales>
                    <MntNeto>39226</MntNeto>
                    <MntExe>0</MntExe>
                    <TasaIVA>19</TasaIVA>
                    <IVA>7453</IVA>
                    <MntTotal>46679</MntTotal>
                </Totales>
            </Encabezado><Detalle>
        <NroLinDet>1</NroLinDet>
        <CdgItem>
            <TpoCodigo>INT</TpoCodigo>
            <VlrCodigo>11</VlrCodigo>
        </CdgItem>
        <NmbItem>[PCU]PEAJE DE RETIRO POR PEAJE UNITARIO VS CARGO UNICO</NmbItem>
        <QtyItem>1</QtyItem>
        <UnmdItem>UN</UnmdItem>
        <PrcItem>27177</PrcItem>
        <MontoItem>27177</MontoItem>
    </Detalle><Detalle>
        <NroLinDet>2</NroLinDet>
        <CdgItem>
            <TpoCodigo>INT</TpoCodigo>
            <VlrCodigo>2</VlrCodigo>
        </CdgItem>
        <NmbItem>POTENCIA
</NmbItem>
        <QtyItem>1</QtyItem>
        <UnmdItem>UN</UnmdItem>
        <PrcItem>12049</PrcItem>
        <MontoItem>12049</MontoItem>
    </Detalle>
    <Referencia>
        <NroLinRef>1</NroLinRef>
        <TpoDocRef></TpoDocRef>
        <FolioRef></FolioRef>
        <FchRef></FchRef>
        <RazonRef></RazonRef>
    </Referencia><Adicional>
                    <NodosA>
                        <A6>Refacturación de Folio 6067</A6>
                    </NodosA>
                </Adicional></Documento>
    </DTE>